oxy/__init__.py
oxy/_internal.py
oxy/exceptions.py
oxy/py.typed
oxy-1.24.0.dist-info/METADATA
oxy-1.24.0.dist-info/WHEEL
oxy-1.24.0.dist-info/RECORD
